falcon_params_verifier/__init__.py
falcon_params_verifier/hook.py
falcon_params_verifier/version.py
falcon_params_verifier-0.1.0.dist-info/METADATA
falcon_params_verifier-0.1.0.dist-info/WHEEL
falcon_params_verifier-0.1.0.dist-info/top_level.txt
falcon_params_verifier-0.1.0.dist-info/RECORD
