Metadata-Version: 2.1
Name: falcon-params-verifier
Version: 0.1.0
Summary: A simple Falcon API "hook" to verify if a provided list of query parameters have been fulfilled.
Home-page: https://github.com/ms7m/falcon-params-verifer
Author: Mustafa Mohamed
Author-email: ms7mohamed@gmail.com
License: MIT
Platform: UNKNOWN
Classifier: License :: OSI Approved :: MIT License
Classifier: Programming Language :: Python
Classifier: Programming Language :: Python :: 3
Classifier: Programming Language :: Python :: 3.6
Classifier: Programming Language :: Python :: Implementation :: CPython
Classifier: Programming Language :: Python :: Implementation :: PyPy
Requires-Python: >=3.6.0
